Metadata-Version: 2.4
Name: test_mkr_021
Version: 0.1.1
Summary: A test package for learning package distribution
Home-page: https://github.com/yourusername/test
Author: Your Name
Author-email: your.email@example.com
Classifier: Programming Language :: Python :: 3
Classifier: License :: OSI Approved :: MIT License
Classifier: Operating System :: OS Independent
Requires-Python: >=3.6
Requires-Dist: numpy>=1.21.0
Requires-Dist: pandas>=1.3.0
Dynamic: author
Dynamic: author-email
Dynamic: classifier
Dynamic: description-content-type
Dynamic: home-page
Dynamic: requires-dist
Dynamic: requires-python
Dynamic: summary
